mapintel/__init__.py
mapintel/app.py
mapintel/config.py
mapintel/py.typed
mapintel-1.0.dist-info/entry_points.txt
mapintel-1.0.dist-info/WHEEL
mapintel-1.0.dist-info/METADATA
mapintel-1.0.dist-info/licenses/LICENSE
mapintel-1.0.dist-info/RECORD
