Metadata-Version: 2.1
Name: mapintel
Version: 1.0
Summary: MapIntel is a system for acquiring intelligence from vast collections of text data by representing each document as a multidimensional vector that captures its own semantics. The system is designed to handle complex Natural Language queries and visual exploration of the corpus.
License: MIT
Author-email: Georgios Douzas <gdouzas@icloud.com>
Requires-Python: >=3.10, <3.12
Classifier: Development Status :: 4 - Beta
Classifier: Intended Audience :: Developers
Classifier: Programming Language :: Python
Classifier: Programming Language :: Python :: 3
Classifier: Programming Language :: Python :: 3 :: Only
Classifier: Programming Language :: Python :: 3.10
Classifier: Programming Language :: Python :: 3.11
Classifier: Topic :: Documentation
Classifier: Topic :: Software Development
Classifier: Topic :: Utilities
Classifier: Typing :: Typed
Requires-Dist: click>=8.1.7
Requires-Dist: colorcet>=3.0.1
Requires-Dist: farm-haystack[aws,inference,opensearch,preprocessing]
Requires-Dist: matplotlib>=3.7.2
Requires-Dist: nicegui>=1.3.13
Requires-Dist: plotly>=5.16.1
Requires-Dist: python-dotenv>=1.0.0
Requires-Dist: sagemaker>=2.183.0
Project-URL: Changelog, https://NOVA-IMS-Innovation-and-Analytics-Lab.github.io/MapIntel/changelog
Project-URL: Discussions, https://github.com/NOVA-IMS-Innovation-and-Analytics-Lab/MapIntel/discussions
Project-URL: Documentation, https://NOVA-IMS-Innovation-and-Analytics-Lab.github.io/MapIntel
Project-URL: Funding, https://github.com/sponsors/NOVA-IMS-Innovation-and-Analytics-Lab
Project-URL: Gitter, https://gitter.im/MapIntel/community
Project-URL: Homepage, https://NOVA-IMS-Innovation-and-Analytics-Lab.github.io/MapIntel
Project-URL: Issues, https://github.com/NOVA-IMS-Innovation-and-Analytics-Lab/MapIntel/issues
Project-URL: Repository, https://github.com/NOVA-IMS-Innovation-and-Analytics-Lab/MapIntel
